LICENSE
leap_model_rebuilder/__init__.py
leap_model_rebuilder/api.py
leap_model_rebuilder/modelexpander.py
leap_model_rebuilder/utils.py
leap_model_rebuilder-0.1.8.dist-info/LICENSE
leap_model_rebuilder-0.1.8.dist-info/METADATA
leap_model_rebuilder-0.1.8.dist-info/WHEEL
leap_model_rebuilder-0.1.8.dist-info/RECORD
