Metadata-Version: 2.1
Name: leap-model-rebuilder
Version: 0.1.8
Summary: 
Home-page: https://github.com/tensorleap/leap-model-rebuilder
License: MIT
Author: dorhar
Author-email: doron.harnoy@tensorleap.ai
Requires-Python: >=3.9,<3.11
Classifier: License :: OSI Approved :: MIT License
Classifier: Programming Language :: Python :: 3
Classifier: Programming Language :: Python :: 3.9
Classifier: Programming Language :: Python :: 3.10
Requires-Dist: protobuf (>=3.19.6,<4.0.0)
Requires-Dist: tensorflow (==2.15.0) ; platform_machine == "x86_64"
Requires-Dist: tensorflow-macos (==2.15.0) ; platform_machine == "arm64"
Project-URL: Repository, https://github.com/tensorleap/leap-model-rebuilder
